README.md
setup.cfg
setup.py
src/pyarcrest/__init__.py
src/pyarcrest/arc.py
src/pyarcrest/errors.py
src/pyarcrest/http.py
src/pyarcrest/x509.py
src/pyarcrest.egg-info/PKG-INFO
src/pyarcrest.egg-info/SOURCES.txt
src/pyarcrest.egg-info/dependency_links.txt
src/pyarcrest.egg-info/entry_points.txt
src/pyarcrest.egg-info/requires.txt
src/pyarcrest.egg-info/top_level.txt
src/pyarcrest/cli/__init__.py
src/pyarcrest/cli/arcrest.py